free_properties/__init__.py
free_properties/_free_property.py
free_properties/_property_array.py
free_properties/_property_factory.py
free_properties-0.3.6.dist-info/LICENSE.txt
free_properties-0.3.6.dist-info/METADATA
free_properties-0.3.6.dist-info/WHEEL
free_properties-0.3.6.dist-info/top_level.txt
free_properties-0.3.6.dist-info/RECORD
