Metadata-Version: 2.1
Name: free-properties
Version: 0.3.6
Summary: Manage properties outside a class
Home-page: https://github.com/yoelcortes/free_properties
Download-URL: https://github.com/yoelcortes/free_properties.git
Author: Yoel Cortes-Pena
Author-email: yoelcortes@gmail.com
License: MIT
Platform: Windows
License-File: LICENSE.txt
